pensando_ent/__init__.py
pensando_ent/example.py
pensando_ent/setup.py
pensando_ent/psm/__init__.py
pensando_ent/psm/api_client.py
pensando_ent/psm/configuration.py
pensando_ent/psm/exceptions.py
pensando_ent/psm/login.py
pensando_ent/psm/model_utils.py
pensando_ent/psm/rest.py
pensando_ent/psm/api/__init__.py
pensando_ent/psm/api/audit_v1_api.py
pensando_ent/psm/api/auth_v1_api.py
pensando_ent/psm/api/browser_v1_api.py
pensando_ent/psm/api/cluster_v1_api.py
pensando_ent/psm/api/diagnostics_v1_api.py
pensando_ent/psm/api/distributedservicecards_v1_api.py
pensando_ent/psm/api/events_v1_api.py
pensando_ent/psm/api/fwlog_v1_api.py
pensando_ent/psm/api/monitoring_v1_api.py
pensando_ent/psm/api/network_v1_api.py
pensando_ent/psm/api/objstore_v1_api.py
pensando_ent/psm/api/orchestration_v1_api.py
pensando_ent/psm/api/preferences_v1_api.py
pensando_ent/psm/api/recoverykeys_v1_api.py
pensando_ent/psm/api/rollout_v1_api.py
pensando_ent/psm/api/routing_v1_api.py
pensando_ent/psm/api/search_v1_api.py
pensando_ent/psm/api/security_v1_api.py
pensando_ent/psm/api/staging_v1_api.py
pensando_ent/psm/api/telemetry_query_v1_api.py
pensando_ent/psm/api/tokenauth_v1_api.py
pensando_ent/psm/api/workload_v1_api.py
pensando_ent/psm/apis/__init__.py
pensando_ent/psm/apis/aggwatch/__init__.py
pensando_ent/psm/apis/audit/__init__.py
pensando_ent/psm/apis/auth/__init__.py
pensando_ent/psm/apis/browser/__init__.py
pensando_ent/psm/apis/cluster/__init__.py
pensando_ent/psm/apis/diagnostics/__init__.py
pensando_ent/psm/apis/events/__init__.py
pensando_ent/psm/apis/fwlog/__init__.py
pensando_ent/psm/apis/monitoring/__init__.py
pensando_ent/psm/apis/network/__init__.py
pensando_ent/psm/apis/objstore/__init__.py
pensando_ent/psm/apis/orchestration/__init__.py
pensando_ent/psm/apis/preferences/__init__.py
pensando_ent/psm/apis/recoverykeys/__init__.py
pensando_ent/psm/apis/rollout/__init__.py
pensando_ent/psm/apis/routing/__init__.py
pensando_ent/psm/apis/search/__init__.py
pensando_ent-1.28.1.dist-info/METADATA
pensando_ent-1.28.1.dist-info/WHEEL
pensando_ent-1.28.1.dist-info/top_level.txt
pensando_ent-1.28.1.dist-info/RECORD
